pyforce/__init__.py
pyforce/agents/__init__.py
pyforce/agents/a2c.py
pyforce/agents/base.py
pyforce/agents/ppo.py
pyforce/env/__init__.py
pyforce/env/action_scaler.py
pyforce/env/base.py
pyforce/env/dict.py
pyforce/env/torch.py
pyforce/memory/__init__.py
pyforce/memory/memory.py
pyforce/nn/__init__.py
pyforce/nn/action/__init__.py
pyforce/nn/action/action_mapper.py
pyforce/nn/hidden/__init__.py
pyforce/nn/hidden/hidden.py
pyforce/nn/observation/__init__.py
pyforce/nn/observation/observation_processor.py
pyforce/nn/value/__init__.py
pyforce/nn/value/value_estimator.py
pyforce/utils/__init__.py
pyforce/utils/rewards.py
pyforce_rl-0.0.11.dist-info/LICENSE
pyforce_rl-0.0.11.dist-info/METADATA
pyforce_rl-0.0.11.dist-info/WHEEL
pyforce_rl-0.0.11.dist-info/top_level.txt
pyforce_rl-0.0.11.dist-info/RECORD
