Metadata-Version: 2.1
Name: pyforce-rl
Version: 0.0.11
Summary: PyForce - A simple reinforcement learning library
Home-page: UNKNOWN
Author: Ole Meyer
Author-email: dev@olemeyer.com
License: UNKNOWN
Platform: UNKNOWN
Requires-Dist: tqdm
Requires-Dist: gym
Requires-Dist: numpy
Requires-Dist: torch
